LICENCE
README.md
setup.py
codificador_de_matrizes_rafaela_ribolla/__init__.py
codificador_de_matrizes_rafaela_ribolla/functions.py
codificador_de_matrizes_rafaela_ribolla.egg-info/PKG-INFO
codificador_de_matrizes_rafaela_ribolla.egg-info/SOURCES.txt
codificador_de_matrizes_rafaela_ribolla.egg-info/dependency_links.txt
codificador_de_matrizes_rafaela_ribolla.egg-info/requires.txt
codificador_de_matrizes_rafaela_ribolla.egg-info/top_level.txt