Metadata-Version: 2.1
Name: codificador-de-matrizes-rafaela-ribolla
Version: 0.0.1
Summary: Codificador de matrizes
Author: Rafaela Afférri e Gustavo Ribolla
Author-email: rafaelaao@al.insper.edu.br
License: MIT License
Keywords: matriz
License-File: LICENCE
